localargo/__about__.py
localargo/__init__.py
localargo/__main__.py
localargo/logging.py
localargo/cli/__init__.py
localargo/cli/commands/__init__.py
localargo/cli/commands/app.py
localargo/cli/commands/ca.py
localargo/cli/commands/cluster.py
localargo/cli/commands/debug.py
localargo/cli/commands/port_forward.py
localargo/cli/commands/secrets.py
localargo/cli/commands/sync.py
localargo/cli/commands/template.py
localargo/cli/commands/up.py
localargo/config/__init__.py
localargo/config/manifest.py
localargo/config/store.py
localargo/core/__init__.py
localargo/core/apps.py
localargo/core/argocd.py
localargo/core/ca.py
localargo/core/catalog.py
localargo/core/checkers.py
localargo/core/cluster.py
localargo/core/coredns.py
localargo/core/execution.py
localargo/core/executors.py
localargo/core/k8s.py
localargo/core/types.py
localargo/eyecandy/__init__.py
localargo/eyecandy/progress_steps.py
localargo/eyecandy/step_logger.py
localargo/eyecandy/table_renderer.py
localargo/eyecandy/tables.py
localargo/providers/__init__.py
localargo/providers/base.py
localargo/providers/kind.py
localargo/providers/registry.py
localargo/utils/__init__.py
localargo/utils/cli.py
localargo/utils/proc.py
localargo/utils/retry.py
localargo-0.3.0.dist-info/METADATA
localargo-0.3.0.dist-info/WHEEL
localargo-0.3.0.dist-info/entry_points.txt
localargo-0.3.0.dist-info/licenses/LICENSE
localargo-0.3.0.dist-info/RECORD
