Metadata-Version: 2.4
Name: localargo
Version: 0.3.0
Project-URL: Documentation, https://github.com/williamkborn/localargo#readme
Project-URL: Issues, https://github.com/williamkborn/localargo/issues
Project-URL: Source, https://github.com/williamkborn/localargo
Author-email: William Born <william.born.git@gmail.com>
License-Expression: MIT
License-File: LICENSE
Classifier: Development Status :: 4 - Beta
Classifier: Programming Language :: Python
Classifier: Programming Language :: Python :: 3.10
Classifier: Programming Language :: Python :: 3.11
Classifier: Programming Language :: Python :: 3.12
Classifier: Programming Language :: Python :: Implementation :: CPython
Classifier: Programming Language :: Python :: Implementation :: PyPy
Requires-Python: >=3.10
Requires-Dist: click
Requires-Dist: pyyaml
Requires-Dist: rich
Requires-Dist: rich-click
Provides-Extra: dev
Requires-Dist: lizard; extra == 'dev'
Requires-Dist: mypy; extra == 'dev'
Requires-Dist: pydoclint; extra == 'dev'
Requires-Dist: pylint; extra == 'dev'
Requires-Dist: pytest; extra == 'dev'
Requires-Dist: types-pyyaml; extra == 'dev'
Provides-Extra: watch
Requires-Dist: watchdog>=2.0.0; extra == 'watch'
